gym_quickcheck/__init__.py
gym_quickcheck/_version.py
gym_quickcheck/envs/__init__.py
gym_quickcheck/envs/alteration_env.py
gym_quickcheck/envs/n_knob_env.py
gym_quickcheck/envs/random_walk_env.py
tests/aux/__init__.py
gym_quickcheck-1.2.1.dist-info/LICENSE
gym_quickcheck-1.2.1.dist-info/METADATA
gym_quickcheck-1.2.1.dist-info/WHEEL
gym_quickcheck-1.2.1.dist-info/top_level.txt
gym_quickcheck-1.2.1.dist-info/RECORD
