Metadata-Version: 2.1
Name: gym-quickcheck
Version: 1.2.1
Summary: Gym environments that allow for coarse but fast testing of AI agents.
Home-page: https://github.com/SwamyDev/gym-quickcheck
Author: Bernhard Raml
Author-email: pypi-reinforcment@googlegroups.com
License: UNKNOWN
Project-URL: Bug Reports, https://github.com/SwamyDev/gym-quickcheck/issues
Project-URL: Source, https://github.com/SwamyDev/gym-quickcheck
Keywords: OpeanAI gym testing continuous integration
Platform: UNKNOWN
Classifier: Development Status :: 3 - Alpha
Classifier: Intended Audience :: Developers
Classifier: Topic :: Scientific/Engineering :: Artificial Intelligence
Classifier: Topic :: Software Development :: Testing
Classifier: License :: OSI Approved :: MIT License
Classifier: Programming Language :: Python :: 3
Requires-Dist: gym
Provides-Extra: test
Requires-Dist: pytest ; extra == 'test'
